agent_proto/__init__.py
agent_proto/agent.py
agent_proto/client.py
agent_proto/data.py
agent_proto/proxy.py
agent_proto/pubsub.py
agent_proto/py.typed
agent_proto/tool.py
agent_proto/tree.py
agent_proto/utils.py
agent_proto-0.0.10.dist-info/METADATA
agent_proto-0.0.10.dist-info/WHEEL
agent_proto-0.0.10.dist-info/RECORD
