Metadata-Version: 2.1
Name: agent-proto
Version: 0.0.10
Summary: 
Author: obahamonde
Author-email: oscar.bahamonde.dev@gmail.com
Requires-Python: >=3.9,<4.0
Classifier: Programming Language :: Python :: 3
Classifier: Programming Language :: Python :: 3.9
Classifier: Programming Language :: Python :: 3.10
Classifier: Programming Language :: Python :: 3.11
Classifier: Programming Language :: Python :: 3.12
Requires-Dist: aiofiles (>=23.2.1,<24.0.0)
Requires-Dist: fastapi (>=0.109.2,<0.110.0)
Requires-Dist: httpx (>=0.25.0,<0.26.0)
Requires-Dist: pydantic (>=2.6.0,<3.0.0)
Requires-Dist: rich (>=13.7.0,<14.0.0)
Requires-Dist: sse-starlette (>=2.0.0,<3.0.0)
Requires-Dist: tenacity (>=8.2.3,<9.0.0)
Requires-Dist: uvicorn (>=0.27.1,<0.28.0)
